kvserver/__init__.py
kvserver/main.py
kvserver/server.py
kvserver/soc_ip.py
kvserver_python-1.1.1.dist-info/METADATA
kvserver_python-1.1.1.dist-info/WHEEL
kvserver_python-1.1.1.dist-info/entry_points.txt
kvserver_python-1.1.1.dist-info/top_level.txt
kvserver_python-1.1.1.dist-info/RECORD
