Metadata-Version: 2.4
Name: kvserver-python
Version: 1.1.1
Summary: A socket server that serve kivy project to kivyclient apk
Author: Odudu otu
Requires-Python: >=3.6
Requires-Dist: keyboard
Requires-Dist: qrcode_term
Requires-Dist: watchdog
Requires-Dist: psutil
Dynamic: author
Dynamic: requires-dist
Dynamic: requires-python
Dynamic: summary
